openfisca_uk_data/__init__.py
openfisca_uk_data/cli.py
openfisca_uk_data/generate.py
openfisca_uk_data/utils.py
openfisca_uk_data/datasets/__init__.py
openfisca_uk_data/datasets/frs/__init__.py
openfisca_uk_data/datasets/frs/frs.py
openfisca_uk_data/datasets/frs/raw_frs.py
openfisca_uk_data/datasets/frs/synth_frs.py
openfisca_uk_data/datasets/frs/frs_enhanced/__init__.py
openfisca_uk_data/datasets/frs/frs_enhanced/frs_enhanced.py
openfisca_uk_data/datasets/frs/frs_enhanced/general.py
openfisca_uk_data/datasets/frs/frs_enhanced/lcf_imputation.py
openfisca_uk_data/datasets/frs/frs_enhanced/spi_imputation.py
openfisca_uk_data/datasets/frs/frs_enhanced/uc_transition.py
openfisca_uk_data/datasets/frs/frs_enhanced/was_imputation.py
openfisca_uk_data/datasets/lcf/__init__.py
openfisca_uk_data/datasets/lcf/raw_lcf.py
openfisca_uk_data/datasets/spi/__init__.py
openfisca_uk_data/datasets/spi/raw_spi.py
openfisca_uk_data/datasets/spi/spi.py
openfisca_uk_data/datasets/was/__init__.py
openfisca_uk_data/datasets/was/raw_was.py
OpenFisca_UK_Data-0.9.0.dist-info/METADATA
OpenFisca_UK_Data-0.9.0.dist-info/WHEEL
OpenFisca_UK_Data-0.9.0.dist-info/entry_points.txt
OpenFisca_UK_Data-0.9.0.dist-info/top_level.txt
OpenFisca_UK_Data-0.9.0.dist-info/RECORD
