Metadata-Version: 2.1
Name: OpenFisca-UK-Data
Version: 0.9.0
Summary: A Python package to manage OpenFisca-UK-compatible microdata
Home-page: http://github.com/PolicyEngine/OpenFisca-UK-Data
Author: Nikhil Woodruff
Author-email: nikhil@policyengine.org
License: UNKNOWN
Platform: UNKNOWN
Requires-Dist: pandas
Requires-Dist: pathlib
Requires-Dist: tqdm
Requires-Dist: h5py
Requires-Dist: tables
Requires-Dist: google-cloud-storage
Requires-Dist: jupyter-book (>=0.11.1)
Requires-Dist: sphinxcontrib-bibtex (>=1.0.0)
Requires-Dist: synthimpute (>=0.1.0)
Requires-Dist: OpenFisca-Tools (>=0.1.3)
